package/__init__.py
package/__main__.py
package/binary_search_algorithm.py
package/input_verification.py
bin_search_stud-1.0.0.dist-info/LICENSE.md
bin_search_stud-1.0.0.dist-info/LICENSE.txt
bin_search_stud-1.0.0.dist-info/METADATA
bin_search_stud-1.0.0.dist-info/WHEEL
bin_search_stud-1.0.0.dist-info/top_level.txt
bin_search_stud-1.0.0.dist-info/RECORD
