Metadata-Version: 2.1
Name: bin-search-stud
Version: 1.0.0
Summary: Это пакет для реализации бинарного поиска
Home-page: UNKNOWN
Author: Болдырев Владимир
Author-email: vladimir.boldyrev.2003@mail.ru
License: UNKNOWN
Platform: UNKNOWN
License-File: LICENSE.md
License-File: LICENSE.txt
